spa/__init__.py
spa/data.py
spa/debug.py
spa/paths.py
spa/ranking.py
spa/spa.py
spa/utils.py
selectiverank-0.0.1.dist-info/LICENSE
selectiverank-0.0.1.dist-info/METADATA
selectiverank-0.0.1.dist-info/WHEEL
selectiverank-0.0.1.dist-info/top_level.txt
selectiverank-0.0.1.dist-info/RECORD
