Metadata-Version: 2.1
Name: selectiverank
Version: 0.0.1
Summary: Implements Selective Preference Aggregation (SPA), a rank aggregation framework that constructs collective rankings while limiting the fraction of individual preferences that can be overruled.
Author: Hayden Mctavish, Berk Ustun
Author-email: Shreyas Kadekodi <skadekodi@ucsd.edu>
License: MIT License
Project-URL: Homepage, https://github.com/ustunb/spa
Project-URL: Bug Tracker, https://github.com/ustunb/spa/issues
Classifier: Programming Language :: Python :: 3
Classifier: License :: OSI Approved :: MIT License
Classifier: Operating System :: OS Independent
Requires-Python: >=3.7
License-File: LICENSE
